qrpypi/__init__.py
qrpypi/qrpypi.py
qrpypi-0.0.8.dist-info/LICENSE
qrpypi-0.0.8.dist-info/METADATA
qrpypi-0.0.8.dist-info/WHEEL
qrpypi-0.0.8.dist-info/top_level.txt
qrpypi-0.0.8.dist-info/RECORD
