Metadata-Version: 2.1
Name: qrpypi
Version: 0.0.8
Summary: A Simple QrCode generator python package
Home-page: https://acnsoft.net/qrpypi.html
Author: AcnSoft
Author-email: info@acnsoft.net
Classifier: Programming Language :: Python :: 3
Classifier: License :: OSI Approved :: MIT License
Classifier: Operating System :: OS Independent
License-File: LICENSE
